bamdash/__init__.py
bamdash/__main__.py
bamdash/command.py
bamdash/scripts/__init__.py
bamdash/scripts/config.py
bamdash/scripts/data.py
bamdash/scripts/plotting.py
bamdash-0.4.5.dist-info/licenses/LICENSE
bamdash-0.4.5.dist-info/METADATA
bamdash-0.4.5.dist-info/WHEEL
bamdash-0.4.5.dist-info/entry_points.txt
bamdash-0.4.5.dist-info/top_level.txt
bamdash-0.4.5.dist-info/RECORD
