Metadata-Version: 2.4
Name: bamdash
Version: 0.4.5
Summary: Create a interactive coverage plot dashboard from bam files and add gb, vcf and bed tracks
Author-email: Jonas Fuchs <jonas.fuchs@uniklinik-freiburg.de>
Maintainer-email: Jonas Fuchs <jonas.fuchs@uniklinik-freiburg.de>
License:                     GNU GENERAL PUBLIC LICENSE
Keywords: pcr, tiled pcr, primer-tiling, qpcr, primer design
Classifier: Programming Language :: Python :: 3.9
Classifier: Programming Language :: Python :: 3.10
Classifier: Programming Language :: Python :: 3.11
Classifier: Programming Language :: Python :: 3.12
Classifier: Programming Language :: Python :: 3.13
Classifier: Operating System :: OS Independent
Requires-Python: <3.14,>=3.9
License-File: LICENSE
Requires-Dist: kaleido>=0.2.1
Requires-Dist: pandas>=1.4.4
Requires-Dist: plotly>=5.17.0
Requires-Dist: pysam>=0.21.0
Requires-Dist: biopython>=1.79
Dynamic: license-file
